LICENSE.txt
README.md
pyproject.toml
setup.cfg
setup.py
data_qualitator/__init__.py
data_qualitator/factory.py
data_qualitator/provider.py
data_qualitator.egg-info/PKG-INFO
data_qualitator.egg-info/SOURCES.txt
data_qualitator.egg-info/dependency_links.txt
data_qualitator.egg-info/requires.txt
data_qualitator.egg-info/top_level.txt
data_qualitator/services/__init__.py
data_qualitator/services/filesystem/__init__.py
data_qualitator/services/filesystem/csv/__init__.py
data_qualitator/services/filesystem/csv/builder.py
data_qualitator/services/filesystem/csv/service.py
data_qualitator/services/filesystem/parquet/__init__.py
data_qualitator/services/filesystem/parquet/builder.py
data_qualitator/services/filesystem/parquet/service.py
data_qualitator/services/gcp/__init__.py
data_qualitator/services/gcp/cloudstorage/__init__.py
data_qualitator/services/gcp/cloudstorage/csv/__init__.py
data_qualitator/services/gcp/cloudstorage/csv/builder.py
data_qualitator/services/gcp/cloudstorage/csv/service.py
data_qualitator/services/gcp/cloudstorage/parquet/__init__.py
data_qualitator/services/gcp/cloudstorage/parquet/builder.py
data_qualitator/services/gcp/cloudstorage/parquet/service.py
data_qualitator/services/sql/__init__.py
data_qualitator/services/sql/builder.py
data_qualitator/services/sql/service.py
data_qualitator/utils/__init__.py
data_qualitator/utils/constants.py
tests/test_filesystem_csv_service.py
tests/test_filesystem_parquet_service.py
tests/test_googlecloudplatform_bigquery_service.py
tests/test_googlecloudplatform_cloudstorage_csv.py
tests/test_googlecloudplatform_cloudstorage_parquet.py
tests/test_postgresql_service.py