Metadata-Version: 2.1
Name: data-qualitator
Version: 1.0.2
Summary: Data quality checking made easy!
Home-page: https://github.com/jmilagroso/data_qualitator
Download-URL: https://github.com/jmilagroso/data_qualitator/releases
Author: Jay Milagroso
Author-email: j.milagroso@gmail.com
License: MIT
Project-URL: Bug Tracker, https://github.com/jmilagroso/data_qualitator/issues
Project-URL: repository, https://github.com/jmilagroso/data_qualitator
Keywords: data quality,great expectations,data accuracy,data completeness,data consistency,data integrity,data validity,data precision,data governance,data cleansing,data profiling,data standardization,data quality assessment,data quality control
Classifier: Development Status :: 4 - Beta
Classifier: Intended Audience :: Developers
Classifier: Topic :: Software Development :: Build Tools
Classifier: License :: OSI Approved :: MIT License
Classifier: Programming Language :: Python :: 3.9
License-File: LICENSE.txt
